AUTHORS
LICENSE
MANIFEST.in
README.rst
requirements.txt
setup.py
openslides_topicvoting/__init__.py
openslides_topicvoting/csv_import.py
openslides_topicvoting/main_menu.py
openslides_topicvoting/models.py
openslides_topicvoting/signals.py
openslides_topicvoting/slides.py
openslides_topicvoting/template.py
openslides_topicvoting/urls.py
openslides_topicvoting/views.py
openslides_topicvoting/voting_system.py
openslides_topicvoting/widgets.py
openslides_topicvoting.egg-info/PKG-INFO
openslides_topicvoting.egg-info/SOURCES.txt
openslides_topicvoting.egg-info/dependency_links.txt
openslides_topicvoting.egg-info/entry_points.txt
openslides_topicvoting.egg-info/requires.txt
openslides_topicvoting.egg-info/top_level.txt
openslides_topicvoting/locale/de/LC_MESSAGES/django.mo
openslides_topicvoting/locale/de/LC_MESSAGES/django.po
openslides_topicvoting/locale/en/LC_MESSAGES/django.po
openslides_topicvoting/static/img/glyphicons_328_podium.png
openslides_topicvoting/static/img/glyphicons_328_podium_white.png
openslides_topicvoting/static/styles/openslides_topicvoting.css
openslides_topicvoting/templates/openslides_topicvoting/ballotpaper.html
openslides_topicvoting/templates/openslides_topicvoting/category_form.html
openslides_topicvoting/templates/openslides_topicvoting/category_list.html
openslides_topicvoting/templates/openslides_topicvoting/category_slide.html
openslides_topicvoting/templates/openslides_topicvoting/category_slide_list.html
openslides_topicvoting/templates/openslides_topicvoting/csv_import.html
openslides_topicvoting/templates/openslides_topicvoting/result.html
openslides_topicvoting/templates/openslides_topicvoting/result_print.html
openslides_topicvoting/templates/openslides_topicvoting/result_slide.html
openslides_topicvoting/templates/openslides_topicvoting/topic_form.html
openslides_topicvoting/templates/openslides_topicvoting/widget_category.html