Metadata-Version: 1.1
Name: openslides-topicvoting
Version: 1.1.0
Summary: OpenSlides Topic Voting Plugin
Home-page: https://github.com/normanjaeckel/openslides-topicvoting/
Author: Authors of OpenSlides Topic Voting Plugin, see AUTHORS
Author-email: openslides-topicvoting@normanjaeckel.de
License: MIT
Keywords: OpenSlides
Platform: UNKNOWN
Classifier: Development Status :: 5 - Production/Stable
Classifier: Environment :: Plugins
Classifier: Environment :: Web Environment
Classifier: Framework :: Django
Classifier: License :: OSI Approved :: MIT License
Classifier: Operating System :: OS Independent
Classifier: Programming Language :: Python :: 2
